odoo/addons/sale_order_report_product_image/README.rst
odoo/addons/sale_order_report_product_image/__init__.py
odoo/addons/sale_order_report_product_image/__manifest__.py
odoo/addons/sale_order_report_product_image/i18n/de.po
odoo/addons/sale_order_report_product_image/i18n/es.po
odoo/addons/sale_order_report_product_image/i18n/pt.po
odoo/addons/sale_order_report_product_image/i18n/sale_order_report_product_image.pot
odoo/addons/sale_order_report_product_image/readme/CONTRIBUTORS.rst
odoo/addons/sale_order_report_product_image/readme/DESCRIPTION.rst
odoo/addons/sale_order_report_product_image/readme/INSTALL.rst
odoo/addons/sale_order_report_product_image/readme/USAGE.rst
odoo/addons/sale_order_report_product_image/static/description/icon.png
odoo/addons/sale_order_report_product_image/static/description/index.html
odoo/addons/sale_order_report_product_image/views/report_saleorder.xml
odoo13_addon_sale_order_report_product_image-13.0.1.0.1.dev5.dist-info/METADATA
odoo13_addon_sale_order_report_product_image-13.0.1.0.1.dev5.dist-info/WHEEL
odoo13_addon_sale_order_report_product_image-13.0.1.0.1.dev5.dist-info/top_level.txt
odoo13_addon_sale_order_report_product_image-13.0.1.0.1.dev5.dist-info/RECORD
